moban_anyconfig/__init__.py
moban_anyconfig/_version.py
moban_anyconfig/adapter.py
moban_anyconfig-0.0.1.dist-info/LICENSE
moban_anyconfig-0.0.1.dist-info/METADATA
moban_anyconfig-0.0.1.dist-info/WHEEL
moban_anyconfig-0.0.1.dist-info/top_level.txt
moban_anyconfig-0.0.1.dist-info/RECORD
